battery_sizing_model/__init__.py
battery_sizing_model/blocks.py
battery_sizing_model/lookup_tables/charge_ocv.pkl
battery_sizing_model/lookup_tables/discharge_ocv.pkl
battery_sizing_model/lookup_tables/soc_interp_points.pkl
battery_sizing_model-0.0.1.dist-info/LICENSE
battery_sizing_model-0.0.1.dist-info/METADATA
battery_sizing_model-0.0.1.dist-info/WHEEL
battery_sizing_model-0.0.1.dist-info/top_level.txt
battery_sizing_model-0.0.1.dist-info/RECORD
