Metadata-Version: 2.1
Name: battery-sizing-model
Version: 0.0.1
Summary: A package for simulating microgrid level battery storage
Author-email: Sean Buchanan <seanbuchanan55@hotmail.com>
Project-URL: repository, https://github.com/seanbuchanan-eng/battery_sizing_model
Project-URL: documentation, https://seanbuchanan-eng.github.io/battery_sizing_model/
Classifier: Programming Language :: Python :: 3
Classifier: License :: OSI Approved :: MIT License
Classifier: Operating System :: Microsoft :: Windows :: Windows 11
Requires-Python: >=3.10
License-File: LICENSE
Requires-Dist: numpy >=1.24.1
